Workbook

Sheet Dashboard
A1: Ambitious Entrepreneurship - Team Dashboard
A2: Team Name: | B2: [Enter Team Name] | D2: Module: | E2: 00
A4: KEY METRICS
A5: Metric | B5: Actual | C5: Target | D5: Status
A6: Total Interviews | B6: ='Interview Log'!B2 | C6: 100+ | D6: =IF(B6>=100,"✓","○")
A7: Interviews, last 7 days | B7: =COUNTIFS('Interview Log'!A:A,">="&(TODAY()-6),'Interview Log'!A:A,"<="&TODAY()) | C7: 15 per student (floor 5) | D7: =IF(B7>=15,"✓","○")
A8: Experiments Completed | B8: =COUNTIF('Experiment Tracker'!F:F,"Complete") | C8: 12+ | D8: =IF(B8>=12,"✓","○")
A9: Tests passed | B9: =COUNTIF('Experiment Tracker'!G:G,"Passed") | C9: -
A10: Total Revenue (€) | B10: ='KPI Tracker'!C18 | C10: 1000+ | D10: =IF(B10>=1000,"✓","○")
A11: Paying Customers | B11: ='KPI Tracker'!C19 | C11: 5+ | D11: =IF(B11>=5,"✓","○")
A13: WEEKLY PROGRESS
A14: Module | B14: Interviews | C14: Experiments | D14: Key Decision
A15: Module 00
A16: Module 01
A17: Module 02
A18: Module 03
A19: Module 04
A20: Module 05
A21: Module 06
A22: Module 07
A23: Module 08
A24: Module 09
A25: Module 10
A26: Module 11
A27: Module 12

Sheet Interview Log
A1: INTERVIEW LOG
A2: Total Interviews: | B2: =COUNTA(A5:A1000) | C2: Target: 100+ over semester
A4: Date | B4: Week # | C4: Interviewee | D4: Role/Persona | E4: Company/Context | F4: Key Insight #1 | G4: Key Insight #2 | H4: Key Insight #3 | I4: Notable Quote | J4: Pain Points (tags) | K4: Follow-up Needed? | L4: Recording Link | M4: Interviewer | N4: Agreed next step | O4: Raised unprompted? (yes/no/n/a) | P4: Cost today (hours or euros) | Q4: Segment
A5: 2025-10-15 | B5: =IF(A5="","",WEEKNUM(A5,1)-WEEKNUM(DATE(YEAR(A5),1,1),1)+1) | C5: Anna M. | D5: Product Manager | E5: Tech Startup | F5: Spends 3h/week on manual reporting | G5: Would pay €50/mo for automation | H5: Tried 2 competitors, both too complex | I5: "I just want it to work without reading docs" | J5: Time waste, Complexity | K5: Yes
B6: =IF(A6="","",WEEKNUM(A6,1)-WEEKNUM(DATE(YEAR(A6),1,1),1)+1)
B7: =IF(A7="","",WEEKNUM(A7,1)-WEEKNUM(DATE(YEAR(A7),1,1),1)+1)
B8: =IF(A8="","",WEEKNUM(A8,1)-WEEKNUM(DATE(YEAR(A8),1,1),1)+1)
B9: =IF(A9="","",WEEKNUM(A9,1)-WEEKNUM(DATE(YEAR(A9),1,1),1)+1)
B10: =IF(A10="","",WEEKNUM(A10,1)-WEEKNUM(DATE(YEAR(A10),1,1),1)+1)
B11: =IF(A11="","",WEEKNUM(A11,1)-WEEKNUM(DATE(YEAR(A11),1,1),1)+1)
B12: =IF(A12="","",WEEKNUM(A12,1)-WEEKNUM(DATE(YEAR(A12),1,1),1)+1)
B13: =IF(A13="","",WEEKNUM(A13,1)-WEEKNUM(DATE(YEAR(A13),1,1),1)+1)
B14: =IF(A14="","",WEEKNUM(A14,1)-WEEKNUM(DATE(YEAR(A14),1,1),1)+1)
B15: =IF(A15="","",WEEKNUM(A15,1)-WEEKNUM(DATE(YEAR(A15),1,1),1)+1)
B16: =IF(A16="","",WEEKNUM(A16,1)-WEEKNUM(DATE(YEAR(A16),1,1),1)+1)
B17: =IF(A17="","",WEEKNUM(A17,1)-WEEKNUM(DATE(YEAR(A17),1,1),1)+1)
... B104: =IF(A104="","",WEEKNUM(A104,1)-WEEKNUM(DATE(YEAR(A104),1,1),1)+1)

Sheet Team
A1: TEAM
A2: Module 01. Every founder confirms the agreement after the end-of-week feedback round. Revisit it on the review date.
A4: FOUNDERS
A5: Founder | B5: Role | C5: Owns these decisions | D5: Tech (1-10) | E5: Product (1-10) | F5: Sales (1-10) | G5: Enjoys most | H5: Hours per week now | I5: Hours per week in 6 months | J5: Confirmed on (date)
A11: AGREEMENT
A12: Topic | B12: What we agreed | C12: Status (agreed, talk it through, dealbreaker) | D12: Revisit by (date)
A13: Shared problem space
A14: Startup or small business, how far, and why
A15: Who decides what, and how we break ties
A16: Time
A17: Money: runway, salary needs, when and how we split equity
A18: How a founder leaves
A19: Our gap and how we close it (learn, recruit, pay)
A20: Feedback routine
A21: Review date
A22: Changes after the end-of-week feedback round

Sheet Ideas
A1: IDEAS
A2: Module 02. One row per idea, written as a problem someone has, not as a product. Mark every score heard (name the person) or assumed.
A3: Our early-stage pitch (one to three sentences: our unique insight, why the problem is worth solving, what our team can execute):
A6: Idea ([who] struggles with [what]) | B6: Source (own itch, expertise or technology, shift in a field, something missing) | C6: Tier (S to F) | D6: Desirable (1-5) | E6: Desirable: heard (name) or assumed | F6: Viable (1-5): money or time spent today | G6: Viable: heard (name) or assumed | H6: Feasible (1-5) | I6: Feasible: heard (name) or assumed | J6: Kept or dropped | K6: Reason

Sheet Pain Map
A1: PAIN MAP
A2: One row per segment, as in the exemplar Pain Map. Mark each cell as heard (name the person) or assumed.
A4: Segment | B4: Who we talked to (name, role) | C4: Frequency | D4: Intensity (one incident costs) | E4: Current spend / workaround | F4: Budget authority?

Sheet Experiment Tracker
A1: EXPERIMENT TRACKER
A2: Build → Measure → Learn
A3: Total: | B3: =COUNTA(A6:A200) | C3: Passed: | D3: =COUNTIF(G:G,"Passed") | E3: Failed: | F3: =COUNTIF(G:G,"Failed")
E4: Methods: Interview, Survey, Landing Page, Prototype, Ad Test, Pricing Test | F4: Status: Planned, Running, Complete | G4: Result: Passed, Failed, Inconclusive (against the line written before the test) | I4: Decision: Go, Pivot, Kill | L4: Evidence level: None (our opinion), Anecdotal, Qualitative interviews, Quantitative (survey or landing page), Wireframe mockup, Functional prototype, Paid. Only Paid validates.
A5: # | B5: Experiment Name | C5: Hypothesis | D5: Success Criteria | E5: Method | F5: Status | G5: Result | H5: Evidence/Data | I5: Decision | J5: Next Action | K5: Date Completed | L5: Evidence level (pyramid rung)
A6: 1 | B6: Problem validation - time waste | C6: PMs spend >2h/week on manual reporting | D6: 8/10 interviewees confirm >2h/week | E6: Interview | F6: Complete | G6: Passed | H6: 9/10 confirmed, avg 3.2h/week | I6: Go | J6: Test solution concepts | K6: 2025-10-20 | L6: Qualitative interviews
A7: =IF(B7="","",ROW()-5)
A8: =IF(B8="","",ROW()-5)
A9: =IF(B9="","",ROW()-5)
A10: =IF(B10="","",ROW()-5)
A11: =IF(B11="","",ROW()-5)
A12: =IF(B12="","",ROW()-5)
A13: =IF(B13="","",ROW()-5)
A14: =IF(B14="","",ROW()-5)
A15: =IF(B15="","",ROW()-5)
A16: =IF(B16="","",ROW()-5)
A17: =IF(B17="","",ROW()-5)
A18: =IF(B18="","",ROW()-5)
... A49: =IF(B49="","",ROW()-5)

Sheet Traffic Sources
A1: TRAFFIC SOURCES
A2: Module 04. One row per source and link. Only visitors and sign-ups from your segment count toward the bar and the line. Ads and friends never count.
A4: Date | B4: Module | C4: Experiment # (Experiment Tracker) | D4: Source (channel and place) | E4: Tagged link (utm_source, utm_content) | F4: Brought by (student) | G4: Segment? (yes, mixed, no) | H4: Visitors | I4: Sign-ups from the segment | J4: Conversion (sign-ups ÷ visitors) | K4: Notes
J5: =IF(OR(H5="",H5=0),"",I5/H5)
J6: =IF(OR(H6="",H6=0),"",I6/H6)
J7: =IF(OR(H7="",H7=0),"",I7/H7)
J8: =IF(OR(H8="",H8=0),"",I8/H8)
J9: =IF(OR(H9="",H9=0),"",I9/H9)
J10: =IF(OR(H10="",H10=0),"",I10/H10)
J11: =IF(OR(H11="",H11=0),"",I11/H11)
J12: =IF(OR(H12="",H12=0),"",I12/H12)
J13: =IF(OR(H13="",H13=0),"",I13/H13)
J14: =IF(OR(H14="",H14=0),"",I14/H14)
J15: =IF(OR(H15="",H15=0),"",I15/H15)
J16: =IF(OR(H16="",H16=0),"",I16/H16)
... J54: =IF(OR(H54="",H54=0),"",I54/H54)

Sheet KPI Tracker
A1: KPI TRACKER
A3: WEEKLY METRICS
A4: Metric | B4: M00 | C4: M01 | D4: M02 | E4: M03 | F4: M04 | G4: M05 | H4: M06 | I4: M07 | J4: M08 | K4: M09 | L4: M10 | M4: M11 | N4: M12
A5: Interviews Conducted
A6: Experiments Run
A7: Landing Page Visitors
A8: Sign-ups / Leads
A9: Prototype Users
A10: Active Users (weekly)
A11: Paying Customers
A12: Revenue (€)
A13: NPS Score
A15: CUMULATIVE TOTALS
A16: Total Interviews | C16: =SUM(B5:N5)
A17: Total Experiments | C17: =SUM(B6:N6)
A18: Total Revenue (€) | C18: =SUM(B12:N12)
A19: Total Customers | C19: =MAX(B11:N11)

Sheet Weekly Reflection
A1: WEEKLY REFLECTION
A2: Complete each week before the next session
A4: Module | B4: What were our 3 biggest learnings this week? | C4: What assumptions did we validate or invalidate? | D4: What surprised us most? | E4: What's our riskiest assumption right now? | F4: What's our #1 priority for next week? | G4: What help do we need?
A5: Module 00
A6: Module 01
A7: Module 02
A8: Module 03
A9: Module 04
A10: Module 05
A11: Module 06
A12: Module 07
A13: Module 08
A14: Module 09
A15: Module 10
A16: Module 11
A17: Module 12

Sheet Self-Assessment
A1: SELF-ASSESSMENT RUBRIC
A2: Track your progress against the grading rubric (GRADING_RUBRIC.md). Evidence quality and decision discipline weigh as much as revenue.
A4: EVIDENCE QUALITY (30%)
A5: Criteria | B5: Your Rating (1-5) | C5: Notes
A6: Interview Log with a named contact and one verbatim quote per conversation
A7: Pre-committed thresholds in the Kill Criteria Log
A8: UTM-verified traffic for landing-page tests
A9: Honest small-n read-outs
A10: The Toolkit tells a complete, auditable story
A12: DECISION DISCIPLINE (30%)
A13: Criteria | B13: Your Rating (1-5) | C13: Notes
A14: Pass/fail lines written BEFORE each test
A15: Lines honoured when a result crossed them
A16: Go/Pivot/Kill decisions argued from data, not attachment
A17: Pivots and kills documented with what the evidence said
A19: VERIFIED TRACTION (30%)
A20: Criteria | B20: Your Rating (1-5) | C20: Notes
A21: Progress along the Revenue Ladder
A22: Revenue from outside your social graph, verified by dashboard or invoice
A23: Repeatable revenue (same offer, more than one customer)
A25: COMMUNICATION (10%)
A26: Criteria | B26: Your Rating (1-5) | C26: Notes
A27: Demo-day pitch with clear problem evidence
A28: Honest numbers
A29: A story that survives Q&A

Sheet Evidence Pack
A1: FINAL SUBMISSION CHECKLIST
A2: Check off items as you complete them
A4: Required Deliverable | B4: Done? | C4: Link/Location | D4: Notes
A5: Final pitch deck (updated with feedback) | B5: ☐
A6: Live demo recording link | B6: ☐
A7: Prototype access (repo or share link) | B7: ☐
A8: Interview log (10-15/week documented) | B8: ☐
A9: Experiment tracker (all experiments) | B9: ☐
A10: Analytics snapshot | B10: ☐
A11: KPI sheet with weekly data | B11: ☐
A12: Individual reflection essay | B12: ☐
A13: Team photo | B13: ☐

Sheet Revenue Ladder
A1: THE REVENUE LADDER — one canonical set of numbers, identical everywhere
A3: Week | B3: Pass bar | C3: Stretch (leaderboard)
A4: Module 08 | B4: First € from outside your social graph | C4: 3 paying users
A5: Module 09 | B5: €500 cumulative | C5: €1,000
A6: Module 10 | B6: €1,000 | C6: €3,000
A7: Module 11 | B7: €2,000 | C7: €5,000
A8: Demo Day | B8: €1,000 verified minimum + evidence pack | C8: The €10,000 club
A10: WHAT COUNTS:
A11: 1. Outside your social graph — no friends, family, classmates, or teams in this course
A12: 2. Verified — payment-dashboard screenshot (Stripe/PayPal) or numbered invoice
A13: 3. Revenue quality ranks: recurring > repeatable offer > paid pilot > custom project
A14: 4. 'Paid twice' beats 'paid once' — repeat customers count extra on the leaderboard
A15: 5. A rigorously argued KILL with a documented evidence pack can earn an A (see GRADING_RUBRIC.md)

Sheet Kill Criteria Log
A1: Date | B1: Module | C1: Experiment | D1: Pre-committed pass/fail threshold | E1: Actual result | F1: Decision (go/pivot/kill) | G1: Committed BEFORE the test? (yes/no)
